logol.py
logol-1.0.0.dist-info/LICENSE
logol-1.0.0.dist-info/WHEEL
logol-1.0.0.dist-info/METADATA
logol-1.0.0.dist-info/RECORD
