Metadata-Version: 2.1
Name: logol
Version: 1.0.0
Summary: Pre-configured logs
Author-email: Joseíto Oliveira <joseito.oliveira@outlook.com>
Classifier: License :: OSI Approved :: MIT License
Project-URL: Home, https://github.com/JoseitoOliveira/logol
